it_eng_python_logger_utils/__init__.py
it_eng_python_logger_utils/logger_utils.py
it_eng_python_logger_utils-1.0.2.dist-info/METADATA
it_eng_python_logger_utils-1.0.2.dist-info/WHEEL
it_eng_python_logger_utils-1.0.2.dist-info/top_level.txt
it_eng_python_logger_utils-1.0.2.dist-info/RECORD
